breezypythongui/__init__.py
breezypythongui/breezypythongui.py
breezypythongui-1.1.2.dist-info/METADATA
breezypythongui-1.1.2.dist-info/WHEEL
breezypythongui-1.1.2.dist-info/top_level.txt
breezypythongui-1.1.2.dist-info/RECORD
