Metadata-Version: 2.1
Name: breezypythongui
Version: 1.1.2
Summary: A simple GUI toolkit for Python
Author: Ken Lambert
Author-email: lambertk@wlu.edu
Classifier: Programming Language :: Python :: 3
Classifier: License :: OSI Approved :: GNU General Public License v3 (GPLv3)
Classifier: Operating System :: OS Independent
Requires-Python: >=3.6
